Metadata-Version: 2.1
Name: discord-py-interactions
Version: 5.13.2
Summary: Easy, simple, scalable and modular: a Python API wrapper for interactions.
Home-page: https://github.com/interactions-py/interactions.py
Author: LordOfPolls
Author-email: dev@lordofpolls.com
Project-URL: Discord, https://discord.gg/KkgMBVuEkx
Project-URL: Documentation, https://interactions-py.github.io/interactions.py/
Classifier: Development Status :: 5 - Production/Stable
Classifier: Framework :: AsyncIO
Classifier: Framework :: aiohttp
Classifier: Intended Audience :: Developers
Classifier: License :: OSI Approved :: MIT License
Classifier: Natural Language :: English
Classifier: Operating System :: OS Independent
Classifier: Programming Language :: Python :: 3
Classifier: Programming Language :: Python :: 3.10
Classifier: Topic :: Software Development :: Libraries
Classifier: Topic :: Software Development :: Libraries :: Python Modules
Classifier: Topic :: Documentation
Classifier: Typing :: Typed
Requires-Python: >=3.10
License-File: LICENSE
Requires-Dist: aiohttp
Requires-Dist: attrs>=22.1
Requires-Dist: audioop-lts; python_version >= "3.13"
Requires-Dist: croniter
Requires-Dist: discord-typings>=0.9.0
Requires-Dist: emoji
Requires-Dist: tomli
Provides-Extra: voice
Requires-Dist: PyNaCl<1.6,>=1.5.0; extra == "voice"
Provides-Extra: speedup
Requires-Dist: aiodns; extra == "speedup"
Requires-Dist: orjson; extra == "speedup"
Requires-Dist: Brotli; extra == "speedup"
Requires-Dist: faust-cchardet; extra == "speedup"
Requires-Dist: uvloop; sys_platform != "win32" and extra == "speedup"
Provides-Extra: sentry
Requires-Dist: sentry-sdk; extra == "sentry"
Provides-Extra: jurigged
Requires-Dist: jurigged; extra == "jurigged"
Provides-Extra: console
Requires-Dist: aioconsole>=0.6.0; extra == "console"
Provides-Extra: all
Requires-Dist: PyNaCl<1.6,>=1.5.0; extra == "all"
Requires-Dist: aiodns; extra == "all"
Requires-Dist: orjson; extra == "all"
Requires-Dist: Brotli; extra == "all"
Requires-Dist: faust-cchardet; extra == "all"
Requires-Dist: uvloop; sys_platform != "win32" and extra == "all"
Requires-Dist: sentry-sdk; extra == "all"
Requires-Dist: jurigged; extra == "all"
Requires-Dist: aioconsole>=0.6.0; extra == "all"
Provides-Extra: docs
Requires-Dist: PyNaCl<1.6,>=1.5.0; extra == "docs"
Requires-Dist: aiodns; extra == "docs"
Requires-Dist: orjson; extra == "docs"
Requires-Dist: Brotli; extra == "docs"
Requires-Dist: faust-cchardet; extra == "docs"
Requires-Dist: uvloop; sys_platform != "win32" and extra == "docs"
Requires-Dist: sentry-sdk; extra == "docs"
Requires-Dist: jurigged; extra == "docs"
Requires-Dist: aioconsole>=0.6.0; extra == "docs"
Requires-Dist: mkdocs-autorefs; extra == "docs"
Requires-Dist: mkdocs-awesome-pages-plugin; extra == "docs"
Requires-Dist: mkdocs-material; extra == "docs"
Requires-Dist: mkdocstrings-python; extra == "docs"
Requires-Dist: mkdocs-minify-plugin; extra == "docs"
Requires-Dist: mkdocs-git-committers-plugin-2; extra == "docs"
Requires-Dist: mkdocs-git-revision-date-localized-plugin; extra == "docs"
Requires-Dist: griffe==0.25; extra == "docs"
Provides-Extra: tests
Requires-Dist: pytest; extra == "tests"
Requires-Dist: pytest-asyncio; extra == "tests"
Requires-Dist: pytest-cov; extra == "tests"
Requires-Dist: python-dotenv; extra == "tests"
Requires-Dist: typeguard; extra == "tests"
Provides-Extra: dev
Requires-Dist: pytest; extra == "dev"
Requires-Dist: pytest-asyncio; extra == "dev"
Requires-Dist: pytest-cov; extra == "dev"
Requires-Dist: python-dotenv; extra == "dev"
Requires-Dist: typeguard; extra == "dev"
Requires-Dist: PyNaCl<1.6,>=1.5.0; extra == "dev"
Requires-Dist: aiodns; extra == "dev"
Requires-Dist: orjson; extra == "dev"
Requires-Dist: Brotli; extra == "dev"
Requires-Dist: faust-cchardet; extra == "dev"
Requires-Dist: uvloop; sys_platform != "win32" and extra == "dev"
Requires-Dist: sentry-sdk; extra == "dev"
Requires-Dist: jurigged; extra == "dev"
Requires-Dist: aioconsole>=0.6.0; extra == "dev"
Requires-Dist: mkdocs-autorefs; extra == "dev"
Requires-Dist: mkdocs-awesome-pages-plugin; extra == "dev"
Requires-Dist: mkdocs-material; extra == "dev"
Requires-Dist: mkdocstrings-python; extra == "dev"
Requires-Dist: mkdocs-minify-plugin; extra == "dev"
Requires-Dist: mkdocs-git-committers-plugin-2; extra == "dev"
Requires-Dist: mkdocs-git-revision-date-localized-plugin; extra == "dev"
Requires-Dist: griffe==0.25; extra == "dev"
Requires-Dist: pre-commit; extra == "dev"
